LICENSE
README.md
setup.py
lysb/__init__.py
lysb.egg-info/PKG-INFO
lysb.egg-info/SOURCES.txt
lysb.egg-info/dependency_links.txt
lysb.egg-info/top_level.txt
lysb/models/LinUCB.py
lysb/models/Thompson.py
lysb/models/__init__.py
lysb/templates/Bandits.py
lysb/templates/__init__.py
lysb/utils/__init__.py
lysb/utils/visualization.py