Metadata-Version: 2.1
Name: lysb
Version: 1.0
Summary: LinUCB implementation in python
Author: Hovhannes Manushyan
Author-email: hovhannes.manushyan@gmail.com
License-File: LICENSE
